passage_auth/__init__.py
passage_auth/admin.py
passage_auth/apps.py
passage_auth/authentication.py
passage_auth/manager.py
passage_auth/models.py
passage_auth/setup.py
passage_auth/tests.py
passage_auth/urls.py
passage_auth/views.py
passage_auth/migrations/0001_initial.py
passage_auth/migrations/__init__.py
drf_passage_identity-0.0.3.dist-info/LICENSE
drf_passage_identity-0.0.3.dist-info/METADATA
drf_passage_identity-0.0.3.dist-info/WHEEL
drf_passage_identity-0.0.3.dist-info/top_level.txt
drf_passage_identity-0.0.3.dist-info/RECORD
